noether_api/__init__.py
noether_api/client.py
noether_api-0.0.6.dist-info/LICENSE
noether_api-0.0.6.dist-info/METADATA
noether_api-0.0.6.dist-info/WHEEL
noether_api-0.0.6.dist-info/top_level.txt
noether_api-0.0.6.dist-info/RECORD
