Metadata-Version: 2.1
Name: noether-api
Version: 0.0.6
Summary: Noether API client library for Python
Author-email: Henry Steinitz <henry@noetherinc.com>
License: Copyright (c) 2018 The Python Packaging Authority        
Project-URL: Homepage, https://noether.dev
Classifier: Programming Language :: Python :: 3
Classifier: License :: OSI Approved :: MIT License
Classifier: Operating System :: OS Independent
Requires-Python: >=3.7
License-File: LICENSE
